LICENSE
README.md
setup.cfg
setup.py
elements_sdk/__init__.py
elements_sdk/api_client.py
elements_sdk/configuration.py
elements_sdk/exceptions.py
elements_sdk/model_utils.py
elements_sdk/rest.py
elements_sdk.egg-info/PKG-INFO
elements_sdk.egg-info/SOURCES.txt
elements_sdk.egg-info/dependency_links.txt
elements_sdk.egg-info/requires.txt
elements_sdk.egg-info/top_level.txt
elements_sdk/api/__init__.py
elements_sdk/api/ai_api.py
elements_sdk/api/auth_api.py
elements_sdk/api/automation_api.py
elements_sdk/api/aws_api.py
elements_sdk/api/click_api.py
elements_sdk/api/integrations_api.py
elements_sdk/api/main_api.py
elements_sdk/api/media_library_api.py
elements_sdk/api/private_api.py
elements_sdk/api/satellite_api.py
elements_sdk/api/sharedstorage_api.py
elements_sdk/api/status_api.py
elements_sdk/api/storage_api.py
elements_sdk/api/tape_archive_api.py
elements_sdk/apis/__init__.py
elements_sdk/model/__init__.py
elements_sdk/model/add_assets_to_click_gallery.py
elements_sdk/model/address.py
elements_sdk/model/ai_annotation.py
elements_sdk/model/ai_annotation_create_request.py
elements_sdk/model/ai_annotation_partial_update.py
elements_sdk/model/ai_annotation_update.py
elements_sdk/model/ai_category.py
elements_sdk/model/ai_category_detail.py
elements_sdk/model/ai_category_detail_partial_update.py
elements_sdk/model/ai_category_detail_update.py
elements_sdk/model/ai_category_mini.py
elements_sdk/model/ai_category_mini_reference.py
elements_sdk/model/ai_combined_inference_result.py
elements_sdk/model/ai_connection.py
elements_sdk/model/ai_dataset.py
elements_sdk/model/ai_dataset_detail.py
elements_sdk/model/ai_dataset_detail_reference.py
elements_sdk/model/ai_dataset_export_request.py
elements_sdk/model/ai_dataset_export_response.py
elements_sdk/model/ai_dataset_reference.py
elements_sdk/model/ai_dataset_with_preview.py
elements_sdk/model/ai_dataset_with_preview_partial_update.py
elements_sdk/model/ai_dataset_with_preview_update.py
elements_sdk/model/ai_image.py
elements_sdk/model/ai_image_reference.py
elements_sdk/model/ai_inference_position.py
elements_sdk/model/ai_metadata.py
elements_sdk/model/ai_model.py
